datamanwithvan/__init__.py
datamanwithvan/datamanwithvan.py
datamanwithvan/config/__init__.py
datamanwithvan/config/config.py
datamanwithvan/data/__init__.py
datamanwithvan/data/datavanquery.py
datamanwithvan/replication/__init__.py
datamanwithvan/replication/replicationjob.py
datamanwithvan/replication/replicationtask.py
datamanwithvan/transport/__init__.py
datamanwithvan/transport/transport.py
datamanwithvan/transport/transport_adlsgen2.py
datamanwithvan/transport/transport_hdfs.py
datamanwithvan/transport/transport_local.py
datamanwithvan/transport/transport_s3.py
datamanwithvan/utils/__init__.py
datamanwithvan/utils/bidirectional_queue.py
datamanwithvan/utils/messages.py
datamanwithvan/utils/statuscodes.py
datamanwithvan/utils/utils.py
datamanwithvan-0.1.9.dist-info/LICENSE
datamanwithvan-0.1.9.dist-info/METADATA
datamanwithvan-0.1.9.dist-info/WHEEL
datamanwithvan-0.1.9.dist-info/entry_points.txt
datamanwithvan-0.1.9.dist-info/top_level.txt
datamanwithvan-0.1.9.dist-info/RECORD
