Metadata-Version: 2.1
Name: datamanwithvan
Version: 0.1.9
Summary: A distributed, parallel datareplication engine that caters to various source/target system combinations and complex corporate environments.
Home-page: https://github.com/vpapakir/datamanwithvan
Author: Evangelos Papakirykou
Author-email: vpapakir@gmail.com
Classifier: Programming Language :: Python :: 3
Classifier: License :: OSI Approved :: MIT License
Classifier: Operating System :: OS Independent
Requires-Python: >=3.6
License-File: LICENSE
Requires-Dist: hdfs
Requires-Dist: impyla
Requires-Dist: azure-storage-file-datalake
Requires-Dist: dynaconf
Requires-Dist: SQLAlchemy
Requires-Dist: pyodbc
Requires-Dist: dask
Requires-Dist: boto3
